{
  "id": "sa-law-a910b5ff-6770-4978-99f5-a9a700f2c140",
  "type": "statute",
  "title": "قواعد التعامل مع الوافدين من مخالفي الأنظمة",
  "title_en": "N/A",
  "short_name": "قواعد التعامل مع الوافدين من مخالفي الأنظمة",
  "status": "in_force",
  "issued_date": "2013-03-24",
  "in_force_date": "2018-11-29",
  "url": "https://laws.boe.gov.sa/BoeLaws/Laws/LawDetails/a910b5ff-6770-4978-99f5-a9a700f2c140/1",
  "description": "تتولى وزارة الداخلية ضبط الوافدين العاملين لحسابهم الخاص، وحالات ترحيل الوافد المخالف، على الشركات والمؤسسات المختصة بخدمات الحجاج والمعتمرين إبلاغ الجهة المختصة عن تأخر أي حاج معتمر عن المغادرة بعد انتهاء المدة المحددة لإقامته، ويجب على الشركات والمؤسسات حصول العمالة الخاصة بهم على الإقامات ورخص العمل، على جميع الأجهزة الحكومية التأكد من أن جميع الوافدين العاملين لديها أو في المجالات والحقول التي تدخل ضمن اختصاصها لديهم تصاريح إقامة سارية المفعول ومصرح لهم بالعمل، أو بموجب عقود رسمية معترف بها، وممنوهع من دخول المملكة كل وافد يُرحَّل.",
  "provisions": [],
  "definitions": []
}
